mqttconsumer/__init__.py
mqttconsumer/mqtt_consumer.py
mqttconsumer-0.3.0.dist-info/LICENSE
mqttconsumer-0.3.0.dist-info/LICENSE_LIBRARIES
mqttconsumer-0.3.0.dist-info/METADATA
mqttconsumer-0.3.0.dist-info/WHEEL
mqttconsumer-0.3.0.dist-info/RECORD
